arch_lint/__init__.py
arch_lint/_full_path.py
arch_lint/_utils.py
arch_lint/error.py
arch_lint/forbidden.py
arch_lint/graph.py
arch_lint/private.py
arch_lint/py.typed
arch_lint/dag/__init__.py
arch_lint/dag/_dag.py
arch_lint/dag/_dag_map.py
arch_lint/dag/check.py
arch_lint-5.0.0.dist-info/WHEEL
arch_lint-5.0.0.dist-info/METADATA
arch_lint-5.0.0.dist-info/RECORD
